[
    {
      "id": 1,
      "title": "Дюна: Частина друга",
      "genre": "Фантастика / 2024",
      "rating": "8.8/10",
      "hall": "Зал 1 (IMAX)",
      "description": "Пол Атрідес веде фременів у війні за Арракіс.",
      "price": 180,
      "dates": ["2025-12-12", "2025-12-13", "2025-12-14"],
      "times": ["18:00", "20:30", "22:00"]
    },
    {
      "id": 2,
      "title": "Аватар: Останній захисник",
      "genre": "Фантастика / 2025",
      "rating": "9.1/10",
      "hall": "Зал 1 (IMAX 3D)",
      "description": "Джейк Саллі захищає Пандору від нової загрози.",
      "price": 200,
      "dates": ["2025-12-15", "2025-12-16"],
      "times": ["17:00", "19:30", "21:45"]
    },
    {
      "id": 3,
      "title": "Місія нездійсненна 8",
      "genre": "Екшн / 2025",
      "rating": "8.7/10",
      "hall": "Зал 2 (Dolby Atmos)",
      "description": "Ітан Гант проти ШІ, що вийшов з-під контролю.",
      "price": 170,
      "dates": ["2025-12-18", "2025-12-19"],
      "times": ["19:15", "21:40"]
    },
    {
      "id": 4,
      "title": "Бетмен 2",
      "genre": "Екшн / 2026",
      "rating": "9.0/10",
      "hall": "Зал 3 (Преміум 4K)",
      "description": "Темний лицар проти Суду Сов.",
      "price": 190,
      "dates": ["2025-12-20", "2025-12-21"],
      "times": ["20:00", "22:30"]
    },
    {
      "id": 5,
      "title": "Вічні: Нове покоління",
      "genre": "Фантастика / 2025",
      "rating": "8.5/10",
      "hall": "Зал 1 (IMAX)",
      "description": "Вічні проти нової космічної загрози.",
      "price": 175,
      "dates": ["2025-12-22", "2025-12-23"],
      "times": ["18:30", "21:00"]
    },
    {
      "id": 6,
      "title": "Форсаж 11",
      "genre": "Екшн / 2025",
      "rating": "8.2/10",
      "hall": "Зал 2 (Комфорт)",
      "description": "Остання гонка Домініка Торетто.",
      "price": 160,
      "dates": ["2025-12-24", "2025-12-25"],
      "times": ["16:00", "19:00", "21:30"]
    },
    {
      "id": 7,
      "title": "Людина-павук: За межами",
      "genre": "Екшн / 2025",
      "rating": "8.9/10",
      "hall": "Зал 1 (IMAX 3D)",
      "description": "Пітер Паркер у мультивсесвіті.",
      "price": 185,
      "dates": ["2025-12-26", "2025-12-27"],
      "times": ["17:30", "20:00"]
    },
    {
      "id": 8,
      "title": "Термінатор: Генезис 2",
      "genre": "Фантастика / 2025",
      "rating": "8.3/10",
      "hall": "Зал 3 (Преміум)",
      "description": "Сара Коннор проти Skynet у новій часовій лінії.",
      "price": 165,
      "dates": ["2025-12-28", "2025-12-29"],
      "times": ["19:45"]
    },
    {
      "id": 9,
      "title": "Скажене весілля",
      "genre": "Комедія / 2025",
      "rating": "8.0/10",
      "hall": "Зал 2 (Комфорт)",
      "description": "Нове весілля — нові пригоди родини Кравчуків!",
      "price": 140,
      "dates": ["2025-12-12", "2025-12-13"],
      "times": ["15:00", "17:30", "20:00"]
    },
    {
      "id": 10,
      "title": "Мавка. Лісова пісня 2",
      "genre": "Анімація / 2025",
      "rating": "8.7/10",
      "hall": "Зал 1 (IMAX)",
      "description": "Мавка повертається, щоб захистити ліс від темряви.",
      "price": 130,
      "dates": ["2025-12-14", "2025-12-15", "2025-12-16"],
      "times": ["11:00", "13:30", "16:00"]
    },
    {
      "id": 11,
      "title": "Гладіатор 2",
      "genre": "Історичний екшн / 2025",
      "rating": "8.9/10",
      "hall": "Зал 3 (Преміум)",
      "description": "Син Максимуса мстить за батька в Колізеї.",
      "price": 175,
      "dates": ["2025-12-17", "2025-12-18"],
      "times": ["19:00", "21:30"]
    },
    {
      "id": 12,
      "title": "Вонка",
      "genre": "Мюзикл / 2023",
      "rating": "7.8/10",
      "hall": "Зал 2 (Комфорт)",
      "description": "Молодий Віллі Вонка будує шоколадну імперію.",
      "price": 150,
      "dates": ["2025-12-19", "2025-12-20"],
      "times": ["14:00", "16:30"]
    },
    {
      "id": 13,
      "title": "Круелла 2",
      "genre": "Драма / 2025",
      "rating": "8.1/10",
      "hall": "Зал 3 (Преміум)",
      "description": "Круелла де Віль проти модної імперії.",
      "price": 160,
      "dates": ["2025-12-21", "2025-12-22"],
      "times": ["18:45"]
    },
    {
      "id": 14,
      "title": "Матриця: Перезавантаження",
      "genre": "Фантастика / 2025",
      "rating": "8.6/10",
      "hall": "Зал 1 (IMAX)",
      "description": "Нео повертається, щоб зламати систему зсередини.",
      "price": 180,
      "dates": ["2025-12-23", "2025-12-24"],
      "times": ["20:00", "22:30"]
    },
    {
      "id": 15,
      "title": "Зоряні війни: Епізод X",
      "genre": "Фантастика / 2025",
      "rating": "9.2/10",
      "hall": "Зал 1 (IMAX 3D)",
      "description": "Нова сага. Рей будує новий Орден джедаїв.",
      "price": 195,
      "dates": ["2025-12-25", "2025-12-26"],
      "times": ["17:00", "19:30", "21:45"]
    },
    {
      "id": 16,
      "title": "Дедпул і Росомаха",
      "genre": "Комедія / 2024",
      "rating": "8.5/10",
      "hall": "Зал 2 (Комфорт)",
      "description": "Дедпул і Росомаха — найгучніший дует Marvel.",
      "price": 165,
      "dates": ["2025-12-27", "2025-12-28"],
      "times": ["18:00", "20:30"]
    },
    {
      "id": 17,
      "title": "Гаррі Поттер: Повернення",
      "genre": "Фентезі / 2025",
      "rating": "9.0/10",
      "hall": "Зал 3 (Преміум)",
      "description": "Гаррі, Рон і Герміона проти нової темряви.",
      "price": 185,
      "dates": ["2025-12-29", "2025-12-30"],
      "times": ["19:30"]
    },
    {
      "id": 18,
      "title": "Титанік 2: Повернення",
      "genre": "Драма / 2025",
      "rating": "8.4/10",
      "hall": "Зал 1 (IMAX)",
      "description": "Нова історія кохання на океанському лайнері.",
      "price": 170,
      "dates": ["2025-12-31", "2026-01-01"],
      "times": ["20:00"]
    },
    {
      "id": 19,
      "title": "Книга джунглів 2",
      "genre": "Анімація / 2025",
      "rating": "8.3/10",
      "hall": "Зал 2 (Комфорт)",
      "description": "Мауглі повертається до джунглів.",
      "price": 135,
      "dates": ["2025-12-30", "2025-12-31"],
      "times": ["12:00", "14:30", "17:00"]
    },
    {
      "id": 20,
      "title": "Україна: 30 років потому",
      "genre": "Документальний / 2025",
      "rating": "9.5/10",
      "hall": "Зал 3 (Преміум)",
      "description": "Історія України від незалежності до сьогодення.",
      "price": 120,
      "dates": ["2025-12-31"],
      "times": ["16:00"]
    }
  ]